{
  "ignorePatterns": [
    {"pattern": "jenkins-mch"},
    {"pattern": "^https://github.com/C2SM-RCM/extpar"},
    {"pattern": "^https://github.com/C2SM-RCM/int2lm"},
    {"pattern": "^https://github.com/C2SM-RCM/cosmo"},
    {"pattern": "^https://github.com/C2SM/icon"},
    {"pattern": "^https://github.com/C2SM/spice"},
    {"pattern": "^https://github.com/C2SM/icontools"},
    {"pattern": "^https://github.com/C2SM/Tasks-Support"},
    {"pattern":"^https://github.com/just-the-docs/just-the-docs-template/generate"}, 
    {"pattern": "^http://cosmo-model.org/"},
    {"pattern": "agupubs.onlinelibrary.wiley.com"},
    {"pattern": ^https://link.springer.com/article},
    {"pattern": "^https://github.com/C2SM/spice"},
    {"pattern": "^https://wiki.iac.ethz.ch/Climphys/ProjectCESM2SetupControlRun"},
    {"pattern": "^https://wiki.iac.ethz.ch/Climphys/ProjectCESM122SetupControlRun"},
    {"pattern": "^https://wiki.iac.ethz.ch/IT/LinuxNetCDF"}
  ]}
